seleniumwire2/__init__.py
seleniumwire2/backend.py
seleniumwire2/exceptions.py
seleniumwire2/handler.py
seleniumwire2/har.py
seleniumwire2/inspect.py
seleniumwire2/options.py
seleniumwire2/py.typed
seleniumwire2/request.py
seleniumwire2/server.py
seleniumwire2/storage.py
seleniumwire2/utils.py
seleniumwire2/webdriver.py
selenium_wire_2-0.2.1.dist-info/AUTHORS.rst
selenium_wire_2-0.2.1.dist-info/LICENSE
selenium_wire_2-0.2.1.dist-info/METADATA
selenium_wire_2-0.2.1.dist-info/NOTICES
selenium_wire_2-0.2.1.dist-info/WHEEL
selenium_wire_2-0.2.1.dist-info/top_level.txt
selenium_wire_2-0.2.1.dist-info/RECORD
